gggg/__init__.py
gggg/cli.py
gggg/gggg.py
gggg-6.0.4.dist-info/METADATA
gggg-6.0.4.dist-info/WHEEL
gggg-6.0.4.dist-info/entry_points.txt
gggg-6.0.4.dist-info/top_level.txt
gggg-6.0.4.dist-info/RECORD
