Metadata-Version: 2.2
Name: gggg
Version: 6.0.4
Requires-Dist: requests
Requires-Dist: rich
Dynamic: requires-dist
